sdci/__init__.py
sdci/__main__.py
sdci/cli.py
sdci/client_service.py
sdci/exceptions.py
sdci/schemas.py
sdci/server.py
sdci/server_runner.py
sdci/settings.py
sdci-0.6.2.dist-info/WHEEL
sdci-0.6.2.dist-info/entry_points.txt
sdci-0.6.2.dist-info/METADATA
sdci-0.6.2.dist-info/RECORD
