Metadata-Version: 2.3
Name: sdci
Version: 0.6.2
Summary: SDCI - Sistema de Deploy Continuo Integrado - Integrated Continuous Deployment System - Sidecar Micro CD
Keywords: continuous-deployment,cd,deployment,server,cli,automation
Author: Jonhnatha Trigueiro
Author-email: Jonhnatha Trigueiro <joepreludian@gmail.com>
Classifier: Development Status :: 3 - Alpha
Classifier: Environment :: Console
Classifier: Environment :: Web Environment
Classifier: Intended Audience :: Developers
Classifier: Intended Audience :: System Administrators
Classifier: Programming Language :: Python :: 3
Classifier: Programming Language :: Python :: 3.13
Classifier: Topic :: Software Development :: Build Tools
Classifier: Topic :: System :: Software Distribution
Requires-Dist: click>=8.2.1
Requires-Dist: fastapi[standard]>=0.116.1
Requires-Dist: keyring>=25.6.0
Requires-Dist: requests>=2.32.4
Requires-Python: >=3.10
Project-URL: Documentation, https://github.com/joepreludian/sdci#readme
Project-URL: Repository, https://github.com/joepreludian/sdci
